llama_index/packs/node_parser_semantic_chunking/__init__.py
llama_index/packs/node_parser_semantic_chunking/base.py
llama_index_packs_node_parser_semantic_chunking-0.4.1.dist-info/METADATA
llama_index_packs_node_parser_semantic_chunking-0.4.1.dist-info/WHEEL
llama_index_packs_node_parser_semantic_chunking-0.4.1.dist-info/licenses/LICENSE
llama_index_packs_node_parser_semantic_chunking-0.4.1.dist-info/RECORD
