Metadata-Version: 2.4
Name: llama-index-packs-node-parser-semantic-chunking
Version: 0.4.1
Summary: llama-index packs node_parser integration
Author-email: Your Name <you@example.com>
Maintainer: jerryjliu
License-Expression: MIT
License-File: LICENSE
Keywords: chunk,chunking,embedding,node,parser,semantic
Requires-Python: <4.0,>=3.9
Requires-Dist: llama-index-core<0.15,>=0.13.0
Requires-Dist: llama-index-embeddings-openai<0.6,>=0.5.0
